kubicle/__init__.py
kubicle/base.py
kubicle/db/conn.py
kubicle/db/models.py
kubicle/log.py
kubicle/runner/base.py
kubicle/runner/dynamic/runner.py
kubicle/runner/k8s/main.py
kubicle/runner/k8s/runner.py
kubicle/runner/process/runner.py
kubicle/server/models.py
kubicle/util.py
kubicle-0.1.29.dist-info/LICENSE
kubicle-0.1.29.dist-info/METADATA
kubicle-0.1.29.dist-info/WHEEL
kubicle-0.1.29.dist-info/RECORD
