Metadata-Version: 2.1
Name: kubicle
Version: 0.1.29
Summary: Background jobs on Kubernetes
License: MIT
Author: Patrick Barker
Author-email: patrickbarkerco@gmail.com
Requires-Python: >=3.10,<4.0
Classifier: License :: OSI Approved :: MIT License
Classifier: Programming Language :: Python :: 3
Classifier: Programming Language :: Python :: 3.10
Classifier: Programming Language :: Python :: 3.11
Classifier: Programming Language :: Python :: 3.12
Requires-Dist: agentcore (>=0.1.0,<0.2.0)
Requires-Dist: kubernetes (>=31.0.0,<32.0.0)
Requires-Dist: pydantic (>=2.8.2,<3.0.0)
Requires-Dist: shortuuid (>=1.0.13,<2.0.0)
Requires-Dist: sqlalchemy (>=2.0.32,<3.0.0)
